datapath.v
// Здесь НИЧЕГО нельзя изменять
module datapath(
  x, y, s, b,
  s_en, s_step, s_sub, s_zero,
  y_en, y_select_next, y_upd,
  clk, rst
);
  input [7:0] x;
  output reg [7:0] y;
  output reg [2:0] s;
  output b;
  
  input s_en, s_sub, s_zero, y_en, y_upd;
  input [1:0] s_step, y_select_next;
  
  input clk, rst;
  
  wire [2:0] s_next;
  
  assign s_next =
    s_sub
    ? (s_zero ? 0 : s) - s_step
    : (s_zero ? 0 : s) + s_step;
  
  always @(posedge clk, posedge rst)
    if(rst) s <= 0;
    else
      if(s_en) s <= s_next;
  
  reg [7:0] y_next;
  
  always @*
    if(y_upd)
      case(y_select_next)
      0: y_next = y;
      1: y_next = y + s;
      2: y_next = y - s;
      3: y_next = y + 1;
      default: y_next = 1'sbx;
      endcase
    else
      y_next = x;
  
  always @(posedge clk, posedge rst)
    if(rst) y <= 0;
    else
      if(y_en) y <= y_next;
  
  assign b = y[s];
endmodule

main.v
// ВНИМАНИЕ!
// Можно изменять ТОЛЬКО части кода, помеченные "(*)",
// и ТОЛЬКО так, как написано у "(*)".
module main(x, on, start, y, s, b, regime, active, clk, rst);
    // // (*) По необходимости можно добавть "reg" в объявлениях выходных точек, задающихся в управляющем автомате.
    input [7:0] x;
    input [1:0] on;
    input start;
    output [7:0] y;
    output [2:0] s;
    output b;
    output reg active;
    output reg [1:0] regime;
    input clk, rst;
  
    // (*) По необходимости можно заменить wire на reg для любых точек далее.
    reg [1:0] y_select_next, s_step;
    reg y_en, s_en, y_upd, s_sub, s_zero;
  
    // Основная часть операционного автомата.
    datapath _datapath(
        .x(x),
        .y(y),
        .s(s),
        .b(b),
        .s_en(s_en),
        .s_step(s_step),
        .s_sub(s_sub),
        .s_zero(s_zero),
        .y_en(y_en),
        .y_select_next(y_select_next),
        .y_upd(y_upd),
        .clk(clk),
        .rst(rst)
    );
    
	localparam M1_S_INC_2_TIMER_TIMEOUT = 2,
	           M2_S_VALUE_TO_INCREASE_Y = 3;
    
    wire should_inc_y;
	
	reg [3:0] state, next_state;
	reg [$clog2(M1_S_INC_2_TIMER_TIMEOUT):0] timer;
	
	localparam STATE_M0 = 0,
               STATE_M0_S1 = 1,
               STATE_M1_S1 = 2,
               STATE_M1_WAIT = 3,
               STATE_M1_S_INC_2 = 4,
               STATE_M2_INC_S = 5,
               STATE_M2_INC_SY = 6,
               STATE_M3_YX = 7,
               STATE_M3_INC_S_Y_MINUS_S = 8,
               STATE_M3_OFF = 9;
  
    // Распознавание свойств данных в операционном автомате.
    // (*) Здесь следует по необходимости объявить новые управляющие точки
    //   и реализовать задающие их подсхемы
    //   (преобразующие данные в управление).
    assign should_inc_y = s == M2_S_VALUE_TO_INCREASE_Y - 2;
  
    // Управляющий автомат.
    // (*) Здесь следует написать схему, основная часть которой - это
    //   типовая реализация управляющего символьного автомата,
    //   заставляющая схему main выполняться согласно условию.   
    
    always @(posedge clk, posedge rst)
        if(rst)
        	begin 
		    	state <= STATE_M0;
		    	timer <= 0;
			end
        else 
        	if (timer == 0) state <= next_state;
        	else timer <= timer - 1;
    		
	always @* begin
	    next_state = 1'bx;
        case(state)
            // on = 0
            STATE_M0, STATE_M0_S1:
                case(on)
                    0: next_state = STATE_M0;
                    1: if (start) next_state = STATE_M1_S1;
                       else next_state = STATE_M0;
                    2: if (start)
                           if (should_inc_y) next_state = STATE_M2_INC_SY;
                           else  next_state = STATE_M2_INC_S;
                       else next_state = STATE_M0;
                    3: next_state = STATE_M3_YX;
                endcase
            // on = 1
            STATE_M1_S1: next_state = STATE_M1_WAIT;
            STATE_M1_WAIT: next_state = STATE_M1_S_INC_2;
            STATE_M1_S_INC_2:
            	begin
            		next_state = STATE_M0_S1;
            		timer = M1_S_INC_2_TIMER_TIMEOUT;
            	end
            // on = 2
            STATE_M2_INC_S, STATE_M2_INC_SY:
                if (!start) next_state = STATE_M0;
                else if (start && should_inc_y) next_state = STATE_M2_INC_SY;
                else next_state = STATE_M2_INC_S;
            // on = 3
            STATE_M3_YX: next_state = STATE_M3_INC_S_Y_MINUS_S;
            STATE_M3_INC_S_Y_MINUS_S: next_state = STATE_M3_OFF;
            STATE_M3_OFF: next_state = STATE_M0;
        endcase
    end
    
    always @* begin
        {active, regime, s_zero, s_step, s_sub, s_en, y_select_next, y_upd, y_en} = 0;
        case(state)
            // on = 0
            STATE_M0_S1:
                begin
	                s_zero = 1;
	                s_step = 1;
	                s_en = 1;
                end
            // on = 1
            STATE_M1_S1:
                begin
                    active = 1;
	                regime = 1;
	                s_zero = 1;
	                s_step = 1;
	                s_en = 1;
                end
            STATE_M1_WAIT:
                begin
                    active = 1;
	                regime = 1;
                end
            STATE_M1_S_INC_2:
                begin
                    active = 1;
	                regime = 1;
	                s_step = 2;
	                s_en = 1;
                end
            // on = 2
            STATE_M2_INC_S:
                begin
	                regime = 2;
	                s_step = 1;
	                s_en = 1;
                end
            STATE_M2_INC_SY:
                begin
	                regime = 2;
	                s_step = 1;
	                s_en = 1;
	                y_select_next = 3;
	                y_upd = 1;
	                y_en = 1;
                end
            // on = 3
            STATE_M3_YX:
                begin
	                regime = 3;
	                y_en = 1;
                end
            STATE_M3_INC_S_Y_MINUS_S:
                begin
	                regime = 3;
	                s_step = 1;
	                s_en = 1;
	                y_select_next = 2;
	                y_upd = 1;
	                y_en = 1;
                end
            STATE_M3_OFF: regime = 3;
        endcase
    end
endmodule

test.v
module test();
	reg clk, rst;
  
	reg [7:0] x;
    reg [1:0] on;
    reg start;
  
	wire [7:0] y;
    wire [2:0] s;
    wire b, active;
    wire [1:0] regime;
	
	initial clk = 0;
	always #1 clk = !clk;
	
	main _main(
		.clk(clk),
		.rst(rst),
		.x(x),
		.on(on),
		.start(start),
		.y(y),
		.s(s),
		.b(b),
		.active(active),
		.regime(regime)
	);
	
	initial begin
		$dumpfile("dump.vcd");
        $dumpvars(1, test);
        x = 8'b10101010;
        
        // on = 2
        //*
        start = 0; on = 2;
        
        rst = 1;
        #2
        rst = 0;
        #4
        
        rst = 1;
        #2
        rst = 0;
        #2
        start = 1;
        #2
       	start = 0;
       	#2
       	
        rst = 1;
        #2
        rst = 0;
        #2
        start = 1;
        #4
        start = 0;
        #2
       	
       	rst = 1;
        #2
        rst = 0;
        #2
        start = 1;
        #6
        start = 0;
        #2
       	
       	rst = 1;
        #2
        rst = 0;
        #2
        start = 1;
        #8
        start = 0;
        #2
        //*/
        
        // on = 3
        //*
        on = 3;
        #2
        on = 0;
       	#6 //*/
        
        // on = 1
		//*
		on = 1;
        #2
        start = 1;
        #12 //*/
        
       	#2
        $finish;
	end
endmodule

dump.vcd
$date
	Sat Dec  6 19:36:03 2025
$end
$version
	Icarus Verilog
$end
$timescale
	1s
$end
$scope module test $end
$var wire 8 ! y [7:0] $end
$var wire 3 " s [2:0] $end
$var wire 2 # regime [1:0] $end
$var wire 1 $ b $end
$var wire 1 % active $end
$var reg 1 & clk $end
$var reg 2 ' on [1:0] $end
$var reg 1 ( rst $end
$var reg 1 ) start $end
$var reg 8 * x [7:0] $end
$upscope $end
$enddefinitions $end
#0
$dumpvars
b10101010 *
0)
1(
b10 '
0&
0%
0$
b0 #
b0 "
b0 !
$end
#1
1&
#2
0&
0(
#3
1&
#4
0&
#5
1&
#6
0&
1(
#7
1&
#8
0&
0(
#9
1&
#10
0&
1)
#11
b10 #
1&
#12
0&
0)
#13
b0 #
b1 "
1&
#14
b0 "
0&
1(
#15
1&
#16
0&
0(
#17
1&
#18
0&
1)
#19
b10 #
1&
#20
0&
#21
b1 "
1&
#22
0&
0)
#23
b0 #
b10 "
1&
#24
b0 "
0&
1(
#25
1&
#26
0&
0(
#27
1&
#28
0&
1)
#29
b10 #
1&
#30
0&
#31
b1 "
1&
#32
0&
#33
b10 #
b10 "
1&
#34
0&
0)
#35
b0 #
b1 !
b11 "
1&
#36
b0 "
b0 !
0&
1(
#37
1&
#38
0&
0(
#39
1&
#40
0&
1)
#41
b10 #
1&
#42
0&
#43
b1 "
1&
#44
0&
#45
b10 #
b10 "
1&
#46
0&
#47
b10 #
b11 "
b1 !
1&
#48
0&
0)
#49
b0 #
b100 "
1&
#50
0&
b11 '
#51
b11 #
1&
#52
0&
b0 '
#53
b11 #
b10101010 !
1&
#54
0&
#55
b11 #
1$
b101 "
b10100110 !
1&
#56
0&
#57
b0 #
1&
#58
0&
b1 '
#59
1&
#60
0&
1)
#61
b1 #
1%
1&
#62
0&
#63
1%
b1 #
b1 "
1&
#64
0&
#65
1%
b1 #
1&
#66
0&
#67
0$
b11 "
1&
#68
0&
#69
1$
b101 "
1&
#70
0&
#71
b111 "
1&
#72
0&
#73
0%
b0 #
b1 "
1&
